LICENSE
MANIFEST.in
setup.py
meg/__init__.py
meg/api.py
meg/app.py
meg/cfg.py
meg/config.default.yml
meg/config.yml
meg/constants.py
meg/db.py
meg/development.py
meg/email.py
meg/exception.py
meg/pgp.py
meg/production.py
meg/sks.py
meg/stalks.py
meg/tests/__init__.py
meg/tests/test_api.py
meg/tests/test_revocation.py
meg/tests/test_stalks.py
meg_server.egg-info/PKG-INFO
meg_server.egg-info/SOURCES.txt
meg_server.egg-info/dependency_links.txt
meg_server.egg-info/entry_points.txt
meg_server.egg-info/requires.txt
meg_server.egg-info/top_level.txt