Metadata-Version: 1.0
Name: meg-server
Version: 0.7.1
Summary: Server component for MEG
Home-page: UNKNOWN
Author: Gregory Rehm and Joshua Lyle
Author-email: UNKNOWN
License: UNKNOWN
Platform: UNKNOWN
